[
  {
    "id": 1,
    "title": "Nutella",
    "description": "De molde Bimbo",
    "price": 200,
    "thumbnail": "Sin imagen",
    "code": "abc124",
    "stock": 25
  },
  {
    "id": 4,
    "title": "Huevos",
    "description": "Docena Grandes",
    "price": 250,
    "thumbnail": "Sin imagen",
    "code": "mno321",
    "stock": 20
  },
  {
    "id": 6,
    "title": "Yogur",
    "description": "Natural La Serenísima",
    "price": 50,
    "thumbnail": "Sin imagen",
    "code": "stu890",
    "stock": 50
  },
  {
    "id": 7,
    "title": "Papel Higiénico",
    "description": "Rollo x4",
    "price": 120,
    "thumbnail": "Sin imagen",
    "code": "vwx123",
    "stock": 15
  },
  {
    "id": 9,
    "title": "Jabón de baño",
    "description": "Aloe Vera",
    "price": 70,
    "thumbnail": "Sin imagen",
    "code": "cdefg6",
    "stock": 45
  },
  {
    "id": 10,
    "title": "Nutella",
    "description": "para crepes",
    "price": 200,
    "thumbnail": "Sin imagen",
    "code": "abc124",
    "stock": 25
  },
  {
    "id": 11,
    "title": "Chocolate ",
    "description": "venido desde holanda",
    "price": 12,
    "thumbnails": [],
    "code": "1212klk",
    "stock": 12,
    "status": true,
    "category": "alsdkls"
  }
]